Workbook
Name phi: '01_premissas'!$B$20
Name va_direto: '01_premissas'!$B$9
Name va_cadeia: '07_resultados'!$B$8
Name va_induzido: '07_resultados'!$B$11
Name transbordo: '07_resultados'!$B$12
Name conf_municipal_reais: '10_municipios'!$B$7

Sheet 00_leia
A1: Planilha final auditável — Opção 2, MIP Ipea + MIP-RS
A2: Unidade de trabalho: R$ milhões de 2025, salvo linha que diga o contrário. Ano cheio: 2037.
A3: Motor: MIP inter-regional Ipea–Receita Federal, 2018, 27 UFs × 68 atividades, release v1 (NF-e). A MIP-RS 2019 é coluna de checagem. As duas contas não se somam.
A6: Bloco | B6: Texto
A7: O que é este arquivo | B7: A conta da operação de nicotina sem fumaça em Santa Cruz do Sul. A matriz que propaga o choque é a MIP Ipea. A MIP-RS 2019 (DEE/SPGG e UFRJ) permanece como ordem de grandeza, com os números já publicados.
A8: Manchete | B8: Tipo I da MIP Ipea no RS: direto da planta mais indireto inter-regional que cai no RS. O induzido é uma rodada à parte e não entra nessa soma. O indireto nos outros estados é o vazamento medido.
A9: O que é dado da revisão 4 | B9: Receita, insumos de R$ 8.000 milhões, valor adicionado direto, 4.060 ocupações, remuneração de R$ 150 mil por ocupação, folha de R$ 114,2 milhões no Sul e R$ 52,8 milhões no RS. Células amarelas.
A10: O que continua estimativa | B10: A abertura de produtos do BOM. A origem geográfica deixou de ser o percentual manual e passou a ser a oferta da TRU ao consumo intermediário do RS.
A11: Fator de preço | B11: φ = IPCA dez/2018 ÷ IPCA dez/2025, SIDRA 1737. A célula nomeada phi está na aba 01. O coeficiente 0,7186 era 2019 e não entra.
A12: Obra | B12: A MAI não casa com a parcela local (máquina importada fora). O número da obra é o da MIP-RS, bloco 2026–2027, e não se soma a 2037.
A13: Conferência municipal | B13: A soma dos 497 municípios, com o ajuste de fechamento em Santa Cruz do Sul, iguala o indireto Ipea no RS mais o induzido no RS. A célula de conferência, em reais, é zero.
A14: O que não somar | B14: Não some Ipea com MIP-RS. Não some o induzido ao tipo I na manchete. Não some a obra a 2037. Não aplique a coluna do fumo sobre a receita.

Sheet 01_premissas
A1: Premissas da planta — revisão 4, intactas
A2: R$ milhões de 2025, ano cheio 2037, com exportação. A receita não é o choque.
A3: Âncoras da revisão 4 de 18/10/2026. O IPCA é SIDRA 1737, número-índice, dezembro.
A6: Item | B6: Valor | C6: Papel
A7: Receita ex-fábrica | B7: 15830 | C7: Teto contábil. Fora do vetor.
A8: Insumos, âncora | B8: 8000 | C8: Base das compras. O vetor publicado fecha em R$ 7.999,97 milhões.
A9: Valor adicionado direto | B9: 7830 | C9: Uma vez, em Santa Cruz do Sul.
A10: Ocupações diretas | B10: 4060 | C10: Estoque de 2037.
A11: Remuneração por ocupação, R$ | B11: 150000 | C11: Com encargos. Premissa v6.
A12: Remuneração direta | B12: =B10*B11/1000000 | C12: Ocupações × remuneração, em R$ milhões.
A13: Folha no Sul | B13: 114.2 | C13: RS + SC + PR.
A14: Folha no RS | B14: 52.8 | C14: 3.007 t. Agricultura do RS.
A15: Folha em Santa Catarina | B15: =(B13-B14)*29/54 | C15: 29/54 do que não é RS.
A16: Folha no Paraná | B16: =(B13-B14)*25/54 | C16: 25/54 do que não é RS.
A17: Toneladas de folha no RS | B17: 3007 | C17: Âncora.
A18: IPCA dezembro de 2018 | B18: 5100.61 | C18: SIDRA 1737.
A19: IPCA dezembro de 2025 | B19: 7403.29 | C19: SIDRA 1737.
A20: phi, 2018 sobre 2025 | B20: =B18/B19 | C20: IPCA 2018 ÷ IPCA 2025.
A21: Propensão a consumir no RS | B21: 0.6 | C21: Uma rodada, só para o induzido.

Sheet 02_bom
A1: Abertura estimada dos produtos — reusada
A2: R$ milhões de 2025. O valor da linha entra no vetor. O percentual manual da rodada anterior fica na coluna ao lado e não define a origem.
A3: Fonte: resultados.json, compras do cenário base, linhas já ancoradas. A origem geográfica está na aba 04.
A6: Linha | B6: Família | C6: Valor (R$ mi) | D6: Percentual manual RS | E6: Produto antigo | F6: Regra antiga, fora do vetor Ipea
A7: Dispositivo e eletrônico do pod | B7: eliq | C7: 6294.7174 | D7: 0.05 | E7: PR066 | F7: 5% RS. Teto MIP PR066 no consumo intermediário: 8,2% local. Pod específico, desconto de especificidade; 85% importado.
A8: Glicerina vegetal do e-líquido | B8: eliq | C8: 18.731444 | D8: 0.35 | E8: PR047 | F8: 35% RS. Piso abaixo da média MIP de químicos orgânicos (PR047, 65% local): glicerina de biodiesel tem oferta gaúcha, sem ser a média do produto.
A9: Propilenoglicol do e-líquido | B9: eliq | C9: 21.853351 | D9: 0.1 | E9: PR047 | F9: 10% RS. Químico orgânico mais específico que a média do PR047; oferta petroquímica concentrada em outros estados.
A10: Aroma do e-líquido | B10: eliq | C10: 60.131319 | D10: 0.15 | E10: PR051 | F10: 15% RS. Abaixo do PR051 (químicos diversos, 40,3% local): aroma composto é especialidade, com peso de importação.
A11: Extração de nicotina além da folha | B11: eliq | C11: 27.066783 | D11: 0.3 | E11: PR051 | F11: 30% RS. Insumo de extração (solvente e processo), entre o PR047 e o PR051. A folha em si não está nesta linha.
A12: Embalagem do pod | B12: eliq | C12: 54.150894 | D12: 0.4 | E12: PR036 | F12: 40% RS. Perto da média MIP do papel e da embalagem (PR036, 39,7% local): caixa e rótulo podem ser impressos no estado.
A13: Químicos do stick | B13: stick | C13: 46.911408 | D13: 0.25 | E13: PR051 | F13: 25% RS. Entre a média do PR051 (40%) e um desconto de especialidade do stick (aroma e ligante).
A14: Papel, filtro e embalagem do stick | B14: stick | C14: 1117.4858 | D14: 0.25 | E14: PR036 | F14: 25% RS. Abaixo do PR036 (39,7%): papel de cigarro e filtro de acetato são mais específicos que a média de papel e embalagem; parte do acetato é importada.
A15: Químicos do sachê | B15: sach | C15: 17.849147 | D15: 0.15 | E15: PR051 | F15: 15% RS. Sachê de exportação, insumo mais específico e mais importado que a média do PR051.
A16: Papel e embalagem do sachê | B16: sach | C16: 14.603847 | D16: 0.3 | E16: PR036 | F16: 30% RS. Entre o PR036 (39,7%) e um desconto de especificidade da lata e do papel do sachê.
A17: Energia elétrica e combustível | B17: eliq | C17: 10.657546 | D17: 1 | E17: PR080 | F17: 100% RS. Energia faturada no estado entra local; o vazamento da geração já está na matriz. MIP PR080: 66% da oferta média é gaúcha — não se usa esse percentual para descontar a fatura.
A18: Energia elétrica e combustível | B18: stick | C18: 28.517198 | D18: 1 | E18: PR080 | F18: 100% RS. Energia faturada no estado entra local; o vazamento da geração já está na matriz. MIP PR080: 66% da oferta média é gaúcha — não se usa esse percentual para descontar a fatura.
... A28: Manutenção | B28: sach | C28: 2.188629 | D28: 0.2 | E28: PR079 | F28: 20% RS. MIP da manutenção (PR079): 30,2% local e 5% importado. Peça de máquina da PMI é mais importada que a média; desconto para 20% RS e 50% importado.
A29: Insumos que não são folha | C29: =SUM(C7:C28)
A30: Folha no Sul | C30: ='01_premissas'!B13
A31: Vetor, insumos | C31: =C29+C30 | F31: Fecha na âncora de 8.000 a menos do resíduo já publicado, cerca de R$ 0,03 milhão.

Sheet 03_ponte
A1: Ponte do BOM para a atividade Ipea de 68
A2: R$ milhões de 2025. A parcela RS é a oferta gaúcha do produto ao consumo intermediário do RS.
A3: Fonte: ipea_ponte_bom.csv. A folha não usa a TRU: vai para a agricultura do RS, de SC e do PR.
A6: Linha | B6: Valor (R$ mi) | C6: Produto na TRU | D6: Atividade Ipea | E6: Parcela RS | F6: Valor no RS | G6: Parcela na atividade ponte
A7: Dispositivo e eletrônico do pod | B7: 6294.7174 | C7: Material eletrônico e equip. de comunicações | D7: Fabricação de equipamentos de informática, produtos eletrônicos e ópticos | E7: 0.40503114 | F7: =B7*E7 | G7: 0.69967874
A8: Glicerina vegetal do e-líquido | B8: 18.731444 | C8: Produtos químicos orgânicos | D8: Fabricação de químicos orgânicos e inorgânicos, resinas e elastômeros | E8: 0.82248225 | F8: =B8*E8 | G8: 0.94406403
A9: Propilenoglicol do e-líquido | B9: 21.853351 | C9: Produtos químicos orgânicos | D9: Fabricação de químicos orgânicos e inorgânicos, resinas e elastômeros | E9: 0.82248225 | F9: =B9*E9 | G9: 0.94406403
A10: Aroma do e-líquido | B10: 60.131319 | C10: Produtos químicos diversos | D10: Fabricação de defensivos, desinfestantes, tintas e químicos diversos | E10: 0.45644565 | F10: =B10*E10 | G10: 0.66418553
A11: Extração de nicotina além da folha | B11: 27.066783 | C11: Produtos químicos diversos | D11: Fabricação de defensivos, desinfestantes, tintas e químicos diversos | E11: 0.45644565 | F11: =B11*E11 | G11: 0.66418553
A12: Embalagem do pod | B12: 54.150894 | C12: Papel, papelão, embalagens e artefatos de papel | D12: Fabricação de celulose, papel e produtos de papel | E12: 0.61769573 | F12: =B12*E12 | G12: 0.97521792
A13: Químicos do stick | B13: 46.911408 | C13: Produtos químicos diversos | D13: Fabricação de defensivos, desinfestantes, tintas e químicos diversos | E13: 0.45644565 | F13: =B13*E13 | G13: 0.66418553
A14: Papel, filtro e embalagem do stick | B14: 1117.4858 | C14: Papel, papelão, embalagens e artefatos de papel | D14: Fabricação de celulose, papel e produtos de papel | E14: 0.61769573 | F14: =B14*E14 | G14: 0.97521792
A15: Químicos do sachê | B15: 17.849147 | C15: Produtos químicos diversos | D15: Fabricação de defensivos, desinfestantes, tintas e químicos diversos | E15: 0.45644565 | F15: =B15*E15 | G15: 0.66418553
A16: Papel e embalagem do sachê | B16: 14.603847 | C16: Papel, papelão, embalagens e artefatos de papel | D16: Fabricação de celulose, papel e produtos de papel | E16: 0.61769573 | F16: =B16*E16 | G16: 0.97521792
A17: Energia elétrica e combustível | B17: 39.493707 | C17: Eletricidade, gás e outras utilidades | D17: Energia elétrica, gás natural e outras utilidades | E17: 0.16921554 | F17: =B17*E17 | G17: 0.99650784
A18: Água | B18: 1.943911 | C18: Água, esgoto, reciclagem e gestão de resíduos | D18: Água, esgoto e gestão de resíduos | E18: 0.99527469 | F18: =B18*E18 | G18: 0.99999978
... A20: Manutenção | B20: 119.33132 | C20: Manutenção, reparação e instalação de máquinas e equipamentos | D20: Manutenção, reparação e instalação de máquinas e equipamentos | E20: 1 | F20: =B20*E20 | G20: 0.8752333
A21: Folha no RS | B21: ='01_premissas'!B14 | C21: Âncora do estudo, não a TRU | D21: Agricultura, inclusive o apoio à agricultura e a pós-colheita | E21: =B21/('01_premissas'!B13) | F21: =B21*E21 | G21: 1
A22: Folha em Santa Catarina | B22: ='01_premissas'!B15 | C22: Âncora do estudo, não a TRU | D22: Agricultura, inclusive o apoio à agricultura e a pós-colheita | E22: =B22/('01_premissas'!B13) | F22: =B22*E22 | G22: 1
A23: Folha no Paraná | B23: ='01_premissas'!B16 | C23: Âncora do estudo, não a TRU | D23: Agricultura, inclusive o apoio à agricultura e a pós-colheita | F23: =B23*E23 | G23: 1
A24: Soma | B24: =SUM(B7:B23) | F24: =SUM(F7:F23)

Sheet 04_origem_uf
A1: Origem por UF — oferta ao consumo intermediário do RS
A2: R$ milhões de 2025. Cada linha de produto soma 100% das UFs. A conferência, em R$ milhões, é zero quando a soma iguala o valor da ponte.
A3: Chave: TRU Usos, participação de cada UF na oferta do produto às 68 atividades do RS. Folha: âncora, agricultura do RS, de SC e do PR.
A5: Conferência da origem, R$ mi | B5: =ROUND((E338-'03_ponte'!B24)*1000000,2) | C5: Zero se a soma por linha iguala o valor da aba 03.
A7: Linha | B7: Grupo | C7: UF | D7: Participação | E7: Valor (R$ mi) | F7: Valor 2018 (R$ mi)
A8: Dispositivo e eletrônico do pod | B8: Dispositivo e eletrônico | C8: RO | D8: 2.1196485e-05 | E8: 0.13342588 | F8: =E8*phi
A9: Dispositivo e eletrônico do pod | B9: Dispositivo e eletrônico | C9: AC | D9: 7.3668268e-05 | E9: 0.46372093 | F9: =E9*phi
A10: Dispositivo e eletrônico do pod | B10: Dispositivo e eletrônico | C10: AM | D10: 0.065845118 | E10: 414.47641 | F10: =E10*phi
A11: Dispositivo e eletrônico do pod | B11: Dispositivo e eletrônico | C11: RR | D11: 9.1033665e-07 | E11: 0.005730312 | F11: =E11*phi
A12: Dispositivo e eletrônico do pod | B12: Dispositivo e eletrônico | C12: PA | D12: 0.00028455764 | E12: 1.7912099 | F12: =E12*phi
A13: Dispositivo e eletrônico do pod | B13: Dispositivo e eletrônico | C13: AP | D13: 3.3757387e-07 | E13: 0.0021249321 | F13: =E13*phi
A14: Dispositivo e eletrônico do pod | B14: Dispositivo e eletrônico | C14: TO | D14: 3.0010179e-05 | E14: 0.1889056 | F14: =E14*phi
A15: Dispositivo e eletrônico do pod | B15: Dispositivo e eletrônico | C15: MA | D15: 5.2614935e-07 | E15: 0.0033119615 | F15: =E15*phi
A16: Dispositivo e eletrônico do pod | B16: Dispositivo e eletrônico | C16: PI | D16: 2.4165664e-06 | E16: 0.015211603 | F16: =E16*phi
A17: Dispositivo e eletrônico do pod | B17: Dispositivo e eletrônico | C17: CE | D17: 5.8192573e-05 | E17: 0.3663058 | F17: =E17*phi
A18: Dispositivo e eletrônico do pod | B18: Dispositivo e eletrônico | C18: RN | D18: 6.0167893e-05 | E18: 0.37873989 | F18: =E18*phi
A19: Dispositivo e eletrônico do pod | B19: Dispositivo e eletrônico | C19: PB | D19: 0.00017340564 | E19: 1.0915395 | F19: =E19*phi
... A337: Folha no Paraná | B337: Folha | C337: PR | D337: 0.24891354 | E337: 28.425926 | F337: =E337*phi
A338: Soma do vetor | E338: =SUM(E8:E337)

Sheet 05_indireto_rs_atividade
A1: Indireto no RS por atividade — MIP Ipea
A2: R$ milhões de 2025. O total é a soma. Esse total é o indireto que cai no RS.
A3: Coeficiente de valor adicionado, remuneração e fator trabalho da própria MIP, sobre x = (I−A)⁻¹ f.
A6: Código | B6: Atividade | C6: Grupo espacial | D6: VA indireto | E6: Remuneração | F6: Ocupações | G6: Produção
A7: A00 | B7: Agricultura, inclusive o apoio à agricultura e a pós-colheita | C7: folha | D7: 58.563101 | E7: 9.6032852 | F7: 1287.9079 | G7: 76.158361
A8: A01 | B8: Pecuária, inclusive o apoio à pecuária | C8: pecuaria | D8: 0.59745203 | E8: 0.18514746 | F8: 33.825385 | G8: 0.92689043
A9: A02 | B9: Produção florestal; pesca e aquicultura | C9: madeira | D9: 9.4093906 | E9: 0.74690847 | F9: 182.81118 | G9: 11.380741
A10: A03 | B10: Extração de carvão mineral e de minerais não-metálicos | C10: extrativa | D10: 0.017762395 | E10: 0.0089912455 | F10: 0.17757614 | G10: 0.53509745
A11: A04 | B11: Extração de petróleo e gás, inclusive as atividades de apoio | C11: extrativa | D11: 0.079899372 | E11: 0.013414626 | F11: 0.027395015 | G11: 1.2836319
A12: A05 | B12: Extração de minério de ferro, inclusive beneficiamentos e a aglomeração | C12: extrativa | D12: 0.0132423 | E12: 0.0013208852 | F12: 0.0071639189 | G12: 0.17401566
A13: A06 | B13: Extração de minerais metálicos não-ferrosos, inclusive beneficiamentos | C13: extrativa | D13: 0.009989755 | E13: 0.0037077579 | F13: 0.028366206 | G13: 0.15094679
A14: A07 | B14: Abate e produtos de carne, inclusive os produtos do laticínio e da pesca | C14: demais_ind | D14: 0.14801843 | E14: 0.097267591 | F14: 1.7026677 | G14: 0.94841946
A15: A08 | B15: Fabricação e refino de açúcar | C15: demais_ind | D15: 0.13509937 | E15: 0.13936533 | F15: 1.7285649 | G15: 0.22933062
A16: A09 | B16: Outros produtos alimentares | C16: demais_ind | D16: 2.3727343 | E16: 1.2728993 | F16: 31.817549 | G16: 19.074624
A17: A10 | B17: Fabricação de bebidas | C17: demais_ind | D17: 0.081953805 | E17: 0.036942311 | F17: 0.48831573 | G17: 0.24354798
A18: A11 | B18: Fabricação de produtos do fumo | C18: demais_ind | D18: 0.0010302556 | E18: 0.00049211818 | F18: 0.0035240836 | G18: 0.022417717
... A74: A67 | B74: Serviços domésticos | C74: sociais | D74: 0 | E74: 0 | F74: 0 | G74: 0
B75: Soma, indireto no RS | D75: =SUM(D7:D74) | E75: =SUM(E7:E74) | F75: =SUM(F7:F74) | G75: =SUM(G7:G74)

Sheet 06_indireto_por_uf
A1: Indireto por UF — vazamento medido
A2: R$ milhões de 2025. O resto do Brasil é a soma menos o RS.
A3: Mesma solução x = (I−A)⁻¹ f. O choque é a origem do BOM. O valor adicionado é o coeficiente da MIP.
A6: UF | B6: Choque | C6: Produção | D6: VA indireto | E6: Ocupações | F6: Remuneração
A7: RO | B7: 1.098267 | C7: 18.354504 | D7: 11.846091 | E7: 128.34146 | F7: 4.9226076
A8: AC | B8: 0.49555181 | C8: 4.5717304 | D8: 3.0441308 | E8: 41.229661 | F8: 1.4922784
A9: AM | B9: 415.96545 | C9: 730.72902 | D9: 63.309012 | E9: 561.8827 | F9: 36.424427
A10: RR | B10: 0.02867177 | C10: 4.3350899 | D10: 2.915318 | E10: 35.010931 | F10: 1.3090635
A11: PA | B11: 3.2911987 | C11: 78.074271 | D11: 38.38576 | E11: 374.96471 | F11: 15.090266
A12: AP | B12: 0.093574503 | C12: 4.5481495 | D12: 3.0807523 | E12: 37.107335 | F12: 1.4043362
A13: TO | B13: 0.37569176 | C13: 16.590564 | D13: 9.8862839 | E13: 125.85382 | F13: 4.3278108
A14: MA | B14: 0.31568675 | C14: 47.920424 | D14: 24.127973 | E14: 275.18102 | F14: 11.174884
A15: PI | B15: 0.16180288 | C15: 16.888318 | D15: 10.457813 | E15: 132.20094 | F15: 4.8645281
A16: CE | B16: 1.3179017 | C16: 77.071974 | D16: 42.808641 | E16: 497.69761 | F16: 20.366174
A17: RN | B17: 0.52814371 | C17: 24.11703 | D17: 14.347597 | E17: 165.6484 | F17: 6.3858518
A18: PB | B18: 1.2889871 | C18: 23.844364 | D18: 14.333822 | E18: 169.24486 | F18: 6.747587
... A33: DF | B33: 12.693897 | C33: 117.03526 | D33: 60.968145 | E33: 477.67764 | F33: 26.662987
A34: Brasil | B34: =SUM(B7:B33) | C34: =SUM(C7:C33) | D34: =SUM(D7:D33) | E34: =SUM(E7:E33) | F34: =SUM(F7:F33)
A35: Resto | B35: =B34-B29 | C35: =C34-C29 | D35: =D34-D29 | E35: =E34-E29 | F35: =F34-F29

Sheet 07_resultados
A1: Resultados — MIP Ipea ao lado da MIP-RS
A2: R$ milhões de 2025 e ocupações. O tipo I da coluna Ipea é fórmula. A coluna MIP-RS é a conta já publicada, para checagem. Não some as colunas.
A3: Indireto Ipea: soma das abas 05 e 06. Induzido: uma rodada, 60% da massa salarial gerada no RS, só a oferta gaúcha. MIP-RS: resultados.json, sem recálculo.
A6: Leitura | B6: MIP Ipea | C6: MIP-RS 2019 | D6: Diferença | E6: Nota
A7: Valor adicionado direto | B7: =va_direto | C7: =va_direto | D7: =B7-C7 | E7: A mesma planta. Na MIP-RS o direto também é R$ 7.830 milhões.
A8: Indireto no RS / cadeia MIP-RS | B8: ='05_indireto_rs_atividade'!D75 | C8: 498.88199 | D8: =B8-C8 | E8: Ipea: soma das 68 atividades. MIP-RS: cadeia já publicada, R$ 498,9 milhões.
A9: Indireto no resto do Brasil | B9: ='06_indireto_por_uf'!D35 | C9: — | D9: — | E9: Vazamento medido. A MIP-RS registrava a compra fora do RS e não a multiplicava.
A10: Tipo I no RS | B10: =B7+B8 | C10: =C7+C8 | D10: =B10-C10 | E10: Manchete Ipea: direto + indireto no RS. A coluna MIP-RS é direto + cadeia.
A11: Induzido no RS, uma rodada, à parte | B11: 627.76114 | C11: 370.80085 | D11: =B11-C11 | E11: Fora da manchete de tipo I. 60% da massa salarial gerada no RS.
A12: Transbordamento no RS (mapa) | B12: =B8+B11 | C12: =C8+C11 | D12: =B12-C12 | E12: O que o mapa reparte. Não é a manchete de tipo I.
A13: Direto + indireto no RS + induzido | B13: =B10+B11 | C13: =C10+C11 | D13: =B13-C13 | E13: Leitura auxiliar. A manchete Ipea permanece o tipo I. O tipo II da MIP-RS é esta coluna.
A14: Ocupações do indireto no RS | B14: ='05_indireto_rs_atividade'!F75 | C14: 4554.975 | D14: =B14-C14 | E14: Fator trabalho da MIP Ipea. MIP-RS: coeficiente da TRU-16.
A15: Ocupações diretas | B15: ='01_premissas'!B10 | C15: 4060 | D15: =B15-C15 | E15: Premissa. Uma vez.
A16: Ocupações do tipo I no RS | B16: =B15+B14 | C16: =C15+C14 | D16: =B16-C16 | E16: Direto + indireto no RS.
A17: Diferença do indireto no RS | B17: =D8/C8 | E17: Fora da banda de 10% a 20%. A origem agora é a NF-e.
A18: Diferença do tipo I no RS | B18: =D10/C10 | E18: Dentro da banda de 10% a 20%, porque o direto de R$ 7.830 milhões é comum.
A19: Conteúdo local dos insumos que não são folha, NF-e | B19: 0.44658942 | C19: 0.098562217 | D19: =B19-C19 | E19: Coluna Ipea: oferta ao RS. Coluna MIP-RS: percentual manual, 9,9%. 44,7% fica fora da banda de 10% a 20%.

Sheet 08_obra
A1: Obra 2026–2027 — número da MIP-RS, fora de 2037
A2: R$ milhões de 2025. Este bloco não entra no ano cheio.
A3: A MAI da fabricação de fumo no RS é receita geral de investimento (máquina 40,4%, veículo 16,0%, construção 10,5%, resto do mundo 38,5%). Não reparte a parcela local já estimada. O efeito permanece o da MIP-RS 2019.
A6: Item | B6: Valor | C6: Origem
A7: CAPEX total | B7: 1634.7145 | C7: Estimativa calibrada, já publicada.
A8: Parcela gaúcha | B8: 483.8755 | C8: Obra civil, montagem e engenharia.
A9: Máquinas e serviços importados | B9: 1150.839 | C9: Fora do choque.
A10: Produção gerada no RS | B10: 740.35629 | C10: MIP-RS 2019.
A11: Valor adicionado no RS | B11: 341.75585 | C11: MIP-RS 2019.
A12: Remunerações | B12: 125.47825 | C12: MIP-RS 2019.
A13: Ocupações do Leontief | B13: 4356.9016 | C13: MIP-RS 2019.
A14: Postos temporários na construção | B14: 2639.4833 | C14: MIP-RS 2019. Fora das 4.060.
A15: ISS em Santa Cruz do Sul | B15: =0.02*0.5*B8 | C15: 2% sobre metade da parcela local. Uma vez, no biênio. Fora de 2037.

Sheet 09_fiscal
A1: Fiscal de referência — premissas, hipótese FUNDOPEM
A2: R$ milhões de 2025. Hipótese de cálculo, não incentivo concedido.
A3: Revisão 4 e Lei 15.642/2021. O desenho de 30% por 96 meses, sem INTEGRAR, permanece.
A6: Canal | B6: Valor | C6: Nota
A7: Tributos sobre o consumo no Brasil | B7: 13700 | C7: Memória da revisão 4.
A8: Dos quais federais | B8: 6580
A9: Tributos sobre o consumo no RS | B9: 928 | C9: Cerca de 6,8% do nacional.
A10: ICMS estadual e municipal no RS | B10: 480 | C10: Base da hipótese.
A11: Cota-parte municipal, 25% | B11: =B10*0.25 | C11: Fórmula.
A12: ICMS estadual líquido da cota | B12: =B10-B11 | C12: Fórmula.
A13: IRPJ/CSLL da planta | B13: 1227.57 | C13: 34% sobre 50% do excedente, com exportação.
A14: Diferimento, 30% de 96 meses | B14: =B10*0.30 | C14: Hipótese. Não é renúncia permanente.
A15: Líquido no ano de fruição | B15: =B10-B14 | C15: Bruto municipal e estadual menos o diferimento.
A16: ISS da obra | B16: ='08_obra'!B15 | C16: Aba 08. Fora de 2037.

Sheet 10_municipios
A1: Transbordamento por município
A2: R$ milhões de 2025. Transbordamento = folha + indústria + serviços + induzido. O direto fica em coluna própria e fora da cor.
A3: Fonte: va_por_municipio.csv, indireto Ipea no RS mais induzido. O ajuste de fechamento volta a Santa Cruz do Sul. A conferência, em reais, é zero.
A5: Ajuste da cadeia, R$ mi | B5: =va_cadeia-SUM(N10:P506) | C5: Volta para serviços de Santa Cruz do Sul.
A6: Ajuste do induzido, R$ mi | B6: =va_induzido-SUM(Q10:Q506) | C6: Volta para o induzido de Santa Cruz do Sul.
A7: Conferência municipal, R$ | B7: =ROUND((G507-va_cadeia-va_induzido)*1000000,2) | C7: Zero se a soma dos 497 municípios iguala o indireto Ipea no RS mais o induzido.
A9: Código IBGE | B9: Município | C9: Folha (R$ mi) | D9: Indústria (R$ mi) | E9: Serviços (R$ mi) | F9: Induzido (R$ mi) | G9: Transbordamento (R$ mi) | H9: VA direto (R$ mi) | I9: COREDE | J9: PAM 2025 (t) | K9: Compra nova 2037 (t) | L9: Distância à sede (km) | N9: Folha CSV | O9: Indústria CSV | P9: Serviços CSV | Q9: Induzido CSV
A10: 4300034 | B10: Aceguá | C10: =N10 | D10: =O10 | E10: =P10 | F10: =Q10 | G10: =C10+D10+E10+F10 | H10: 0 | I10: 0 | J10: 0 | K10: 0 | L10: 281 | N10: 0 | O10: 0 | P10: 0 | Q10: 0.005442
A11: 4300059 | B11: Água Santa | C11: =N11 | D11: =O11 | E11: =P11 | F11: =Q11 | G11: =C11+D11+E11+F11 | H11: 0 | I11: 0 | J11: 0 | K11: 0 | L11: 162.6 | N11: 0 | O11: 0.136533 | P11: 0.158337 | Q11: 0.304659
A12: 4300109 | B12: Agudo | C12: =N12 | D12: =O12 | E12: =P12 | F12: =Q12 | G12: =C12+D12+E12+F12 | H12: 0 | I12: 0 | J12: 4400 | K12: 37.84 | L12: 79.4 | N12: 0.736373 | O12: 0.830545 | P12: 0.92364 | Q12: 0.887491
A13: 4300208 | B13: Ajuricaba | C13: =N13 | D13: =O13 | E13: =P13 | F13: =Q13 | G13: =C13+D13+E13+F13 | H13: 0 | I13: 0 | J13: 0 | K13: 0 | L13: 205.3 | N13: 0 | O13: 0.083235 | P13: 0.148069 | Q13: 0.089908
A14: 4300307 | B14: Alecrim | C14: =N14 | D14: =O14 | E14: =P14 | F14: =Q14 | G14: =C14+D14+E14+F14 | H14: 0 | I14: 0 | J14: 30 | K14: 0.258 | L14: 320.6 | N14: 0.005021 | O14: 0 | P14: 0 | Q14: 0.01242
A15: 4300406 | B15: Alegrete | C15: =N15 | D15: =O15 | E15: =P15 | F15: =Q15 | G15: =C15+D15+E15+F15 | H15: 0 | I15: 0 | J15: 0 | K15: 0 | L15: 331.8 | N15: 0 | O15: 0 | P15: 0 | Q15: 0.006054
A16: 4300455 | B16: Alegria | C16: =N16 | D16: =O16 | E16: =P16 | F16: =Q16 | G16: =C16+D16+E16+F16 | H16: 0 | I16: 0 | J16: 0 | K16: 0 | L16: 259.2 | N16: 0 | O16: 0.024037 | P16: 0.045691 | Q16: 0.031591
A17: 4300471 | B17: Almirante Tamandaré do Sul | C17: =N17 | D17: =O17 | E17: =P17 | F17: =Q17 | G17: =C17+D17+E17+F17 | H17: 0 | I17: 0 | J17: 0 | K17: 0 | L17: 175.1 | N17: 0 | O17: 0.170583 | P17: 0.076204 | Q17: 0.131571
A18: 4300505 | B18: Alpestre | C18: =N18 | D18: =O18 | E18: =P18 | F18: =Q18 | G18: =C18+D18+E18+F18 | H18: 0 | I18: 0 | J18: 2220 | K18: 19.092 | L18: 276.8 | N18: 0.371534 | O18: 0 | P18: 0 | Q18: 0.049405
A19: 4300554 | B19: Alto Alegre | C19: =N19 | D19: =O19 | E19: =P19 | F19: =Q19 | G19: =C19+D19+E19+F19 | H19: 0 | I19: 0 | J19: 0 | K19: 0 | L19: 109.1 | N19: 0 | O19: 0.114226 | P19: 0.157702 | Q19: 0.230637
A20: 4300570 | B20: Alto Feliz | C20: =N20 | D20: =O20 | E20: =P20 | F20: =Q20 | G20: =C20+D20+E20+F20 | H20: 0 | I20: 0 | J20: 0 | K20: 0 | L20: 111.3 | N20: 0 | O20: 0.615003 | P20: 0.151102 | Q20: 0.891853
A21: 4300604 | B21: Alvorada | C21: =N21 | D21: =O21 | E21: =P21 | F21: =Q21 | G21: =C21+D21+E21+F21 | H21: 0 | I21: 0 | J21: 0 | K21: 0 | L21: 137.8 | N21: 0 | O21: 17.315243 | P21: 1.229372 | Q21: 6.765189
... A372: 4316758 | B372: Santa Clara do Sul | C372: =N372 | D372: =O372 | E372: =P372 | F372: =Q372 | G372: =C372+D372+E372+F372 | H372: 0 | I372: 0 | J372: 228 | K372: 1.961 | L372: 34.1 | N372: 0.038158 | O372: 1.551271 | P372: 1.076084 | Q372: 1.714758
A373: 4316808 | B373: Santa Cruz do Sul | C373: =N373 | D373: =O373 | E373: =P373+$B$5 | F373: =Q373+$B$6 | G373: =C373+D373+E373+F373 | H373: 7830 | I373: 1 | J373: 12610 | K373: 108.446 | L373: 0 | N373: 2.110379 | O373: 78.706507 | P373: 154.82804 | Q373: 222.47617
A374: 4316907 | B374: Santa Maria | C374: =N374 | D374: =O374 | E374: =P374 | F374: =Q374 | G374: =C374+D374+E374+F374 | H374: 0 | I374: 0 | J374: 104 | K374: 0.894 | L374: 137.9 | N374: 0.017405 | O374: 15.23519 | P374: 2.634975 | Q374: 1.364655
A375: 4316956 | B375: Santa Maria do Herval | C375: =N375 | D375: =O375 | E375: =P375 | F375: =Q375 | G375: =C375+D375+E375+F375 | H375: 0 | I375: 0 | J375: 3 | K375: 0.026 | L375: 140.5 | N375: 0.000502 | O375: 0.49763 | P375: 0.279384 | Q375: 1.167031
A376: 4316972 | B376: Santa Margarida do Sul | C376: =N376 | D376: =O376 | E376: =P376 | F376: =Q376 | G376: =C376+D376+E376+F376 | H376: 0 | I376: 0 | J376: 0 | K376: 0 | L376: 181.7 | N376: 0 | O376: 0.044667 | P376: 0.060727 | Q376: 0.033734
A377: 4317004 | B377: Santana da Boa Vista | C377: =N377 | D377: =O377 | E377: =P377 | F377: =Q377 | G377: =C377+D377+E377+F377 | H377: 0 | I377: 0 | J377: 2 | K377: 0.017 | L377: 149.5 | N377: 0.000335 | O377: 0.038356 | P377: 0.18275 | Q377: 0.160307
A378: 4317103 | B378: Sant'ana do Livramento | C378: =N378 | D378: =O378 | E378: =P378 | F378: =Q378 | G378: =C378+D378+E378+F378 | H378: 0 | I378: 0 | J378: 0 | K378: 0 | L378: 326.9 | N378: 0 | O378: 0 | P378: 0 | Q378: 0.004845
A379: 4317202 | B379: Santa Rosa | C379: =N379 | D379: =O379 | E379: =P379 | F379: =Q379 | G379: =C379+D379+E379+F379 | H379: 0 | I379: 0 | J379: 0 | K379: 0 | L379: 284 | N379: 0 | O379: 0 | P379: 0 | Q379: 0.081391
A380: 4317251 | B380: Santa Tereza | C380: =N380 | D380: =O380 | E380: =P380 | F380: =Q380 | G380: =C380+D380+E380+F380 | H380: 0 | I380: 0 | J380: 0 | K380: 0 | L380: 86.2 | N380: 0 | O380: 0.199952 | P380: 0.126941 | Q380: 0.58381
A381: 4317301 | B381: Santa Vitória do Palmar | C381: =N381 | D381: =O381 | E381: =P381 | F381: =Q381 | G381: =C381+D381+E381+F381 | H381: 0 | I381: 0 | J381: 0 | K381: 0 | L381: 394.3 | N381: 0 | O381: 0 | P381: 0 | Q381: 0.000327
A382: 4317400 | B382: Santiago | C382: =N382 | D382: =O382 | E382: =P382 | F382: =Q382 | G382: =C382+D382+E382+F382 | H382: 0 | I382: 0 | J382: 258 | K382: 2.219 | L382: 238.8 | N382: 0.043178 | O382: 0.29143 | P382: 0.336608 | Q382: 0.0773
A383: 4317509 | B383: Santo Ângelo | C383: =N383 | D383: =O383 | E383: =P383 | F383: =Q383 | G383: =C383+D383+E383+F383 | H383: 0 | I383: 0 | J383: 0 | K383: 0 | L383: 240.6 | N383: 0 | O383: 2.037055 | P383: 0.450004 | Q383: 0.154005
A384: 4317558 | B384: Santo Antônio do Palma | C384: =N384 | D384: =O384 | E384: =P384 | F384: =Q384 | G384: =C384+D384+E384+F384 | H384: 0 | I384: 0 | J384: 63 | K384: 0.542 | L384: 133.4 | N384: 0.010544 | O384: 0.159538 | P384: 0.12211 | Q384: 0.329614
A385: 4317608 | B385: Santo Antônio da Patrulha | C385: =N385 | D385: =O385 | E385: =P385 | F385: =Q385 | G385: =C385+D385+E385+F385 | H385: 0 | I385: 0 | J385: 4 | K385: 0.034 | L385: 180.3 | N385: 0.000669 | O385: 2.810666 | P385: 0.557954 | Q385: 2.02597
... A506: 4323804 | B506: Xangri-Lá | C506: =N506 | D506: =O506 | E506: =P506 | F506: =Q506 | G506: =C506+D506+E506+F506 | H506: 0 | I506: 0 | J506: 0 | K506: 0 | L506: 226.7 | N506: 0 | O506: 0.238144 | P506: 0.330388 | Q506: 0.661406
B507: TOTAL | C507: =SUM(C10:C506) | D507: =SUM(D10:D506) | E507: =SUM(E10:E506) | F507: =SUM(F10:F506) | G507: =SUM(G10:G506) | H507: =SUM(H10:H506)

Sheet 11_corede
A1: COREDE Vale do Rio Pardo
A2: R$ milhões de 2025. Cada valor é SOMASE do código IBGE na aba 10.
A3: Artigo 3º do estatuto. 23 municípios. Gramado Xavier fica de fora.
A6: Código IBGE | B6: Município | C6: Transbordamento | D6: Folha | E6: Indústria | F6: Serviços | G6: Induzido
A7: 4316808 | B7: =INDEX('10_municipios'!$B$10:$B$506,MATCH(A7,'10_municipios'!$A$10:$A$506,0)) | C7: =INDEX('10_municipios'!$G$10:$G$506,MATCH(A7,'10_municipios'!$A$10:$A$506,0)) | D7: =INDEX('10_municipios'!$C$10:$C$506,MATCH(A7,'10_municipios'!$A$10:$A$506,0)) | E7: =INDEX('10_municipios'!$D$10:$D$506,MATCH(A7,'10_municipios'!$A$10:$A$506,0)) | F7: =INDEX('10_municipios'!$E$10:$E$506,MATCH(A7,'10_municipios'!$A$10:$A$506,0)) | G7: =INDEX('10_municipios'!$F$10:$F$506,MATCH(A7,'10_municipios'!$A$10:$A$506,0))
A8: 4322608 | B8: =INDEX('10_municipios'!$B$10:$B$506,MATCH(A8,'10_municipios'!$A$10:$A$506,0)) | C8: =INDEX('10_municipios'!$G$10:$G$506,MATCH(A8,'10_municipios'!$A$10:$A$506,0)) | D8: =INDEX('10_municipios'!$C$10:$C$506,MATCH(A8,'10_municipios'!$A$10:$A$506,0)) | E8: =INDEX('10_municipios'!$D$10:$D$506,MATCH(A8,'10_municipios'!$A$10:$A$506,0)) | F8: =INDEX('10_municipios'!$E$10:$E$506,MATCH(A8,'10_municipios'!$A$10:$A$506,0)) | G8: =INDEX('10_municipios'!$F$10:$F$506,MATCH(A8,'10_municipios'!$A$10:$A$506,0))
A9: 4322707 | B9: =INDEX('10_municipios'!$B$10:$B$506,MATCH(A9,'10_municipios'!$A$10:$A$506,0)) | C9: =INDEX('10_municipios'!$G$10:$G$506,MATCH(A9,'10_municipios'!$A$10:$A$506,0)) | D9: =INDEX('10_municipios'!$C$10:$C$506,MATCH(A9,'10_municipios'!$A$10:$A$506,0)) | E9: =INDEX('10_municipios'!$D$10:$D$506,MATCH(A9,'10_municipios'!$A$10:$A$506,0)) | F9: =INDEX('10_municipios'!$E$10:$E$506,MATCH(A9,'10_municipios'!$A$10:$A$506,0)) | G9: =INDEX('10_municipios'!$F$10:$F$506,MATCH(A9,'10_municipios'!$A$10:$A$506,0))
A10: 4315701 | B10: =INDEX('10_municipios'!$B$10:$B$506,MATCH(A10,'10_municipios'!$A$10:$A$506,0)) | C10: =INDEX('10_municipios'!$G$10:$G$506,MATCH(A10,'10_municipios'!$A$10:$A$506,0)) | D10: =INDEX('10_municipios'!$C$10:$C$506,MATCH(A10,'10_municipios'!$A$10:$A$506,0)) | E10: =INDEX('10_municipios'!$D$10:$D$506,MATCH(A10,'10_municipios'!$A$10:$A$506,0)) | F10: =INDEX('10_municipios'!$E$10:$E$506,MATCH(A10,'10_municipios'!$A$10:$A$506,0)) | G10: =INDEX('10_municipios'!$F$10:$F$506,MATCH(A10,'10_municipios'!$A$10:$A$506,0))
A11: 4304200 | B11: =INDEX('10_municipios'!$B$10:$B$506,MATCH(A11,'10_municipios'!$A$10:$A$506,0)) | C11: =INDEX('10_municipios'!$G$10:$G$506,MATCH(A11,'10_municipios'!$A$10:$A$506,0)) | D11: =INDEX('10_municipios'!$C$10:$C$506,MATCH(A11,'10_municipios'!$A$10:$A$506,0)) | E11: =INDEX('10_municipios'!$D$10:$D$506,MATCH(A11,'10_municipios'!$A$10:$A$506,0)) | F11: =INDEX('10_municipios'!$E$10:$E$506,MATCH(A11,'10_municipios'!$A$10:$A$506,0)) | G11: =INDEX('10_municipios'!$F$10:$F$506,MATCH(A11,'10_municipios'!$A$10:$A$506,0))
A12: 4322533 | B12: =INDEX('10_municipios'!$B$10:$B$506,MATCH(A12,'10_municipios'!$A$10:$A$506,0)) | C12: =INDEX('10_municipios'!$G$10:$G$506,MATCH(A12,'10_municipios'!$A$10:$A$506,0)) | D12: =INDEX('10_municipios'!$C$10:$C$506,MATCH(A12,'10_municipios'!$A$10:$A$506,0)) | E12: =INDEX('10_municipios'!$D$10:$D$506,MATCH(A12,'10_municipios'!$A$10:$A$506,0)) | F12: =INDEX('10_municipios'!$E$10:$E$506,MATCH(A12,'10_municipios'!$A$10:$A$506,0)) | G12: =INDEX('10_municipios'!$F$10:$F$506,MATCH(A12,'10_municipios'!$A$10:$A$506,0))
A13: 4320677 | B13: =INDEX('10_municipios'!$B$10:$B$506,MATCH(A13,'10_municipios'!$A$10:$A$506,0)) | C13: =INDEX('10_municipios'!$G$10:$G$506,MATCH(A13,'10_municipios'!$A$10:$A$506,0)) | D13: =INDEX('10_municipios'!$C$10:$C$506,MATCH(A13,'10_municipios'!$A$10:$A$506,0)) | E13: =INDEX('10_municipios'!$D$10:$D$506,MATCH(A13,'10_municipios'!$A$10:$A$506,0)) | F13: =INDEX('10_municipios'!$E$10:$E$506,MATCH(A13,'10_municipios'!$A$10:$A$506,0)) | G13: =INDEX('10_municipios'!$F$10:$F$506,MATCH(A13,'10_municipios'!$A$10:$A$506,0))
A14: 4301206 | B14: =INDEX('10_municipios'!$B$10:$B$506,MATCH(A14,'10_municipios'!$A$10:$A$506,0)) | C14: =INDEX('10_municipios'!$G$10:$G$506,MATCH(A14,'10_municipios'!$A$10:$A$506,0)) | D14: =INDEX('10_municipios'!$C$10:$C$506,MATCH(A14,'10_municipios'!$A$10:$A$506,0)) | E14: =INDEX('10_municipios'!$D$10:$D$506,MATCH(A14,'10_municipios'!$A$10:$A$506,0)) | F14: =INDEX('10_municipios'!$E$10:$E$506,MATCH(A14,'10_municipios'!$A$10:$A$506,0)) | G14: =INDEX('10_municipios'!$F$10:$F$506,MATCH(A14,'10_municipios'!$A$10:$A$506,0))
A15: 4314076 | B15: =INDEX('10_municipios'!$B$10:$B$506,MATCH(A15,'10_municipios'!$A$10:$A$506,0)) | C15: =INDEX('10_municipios'!$G$10:$G$506,MATCH(A15,'10_municipios'!$A$10:$A$506,0)) | D15: =INDEX('10_municipios'!$C$10:$C$506,MATCH(A15,'10_municipios'!$A$10:$A$506,0)) | E15: =INDEX('10_municipios'!$D$10:$D$506,MATCH(A15,'10_municipios'!$A$10:$A$506,0)) | F15: =INDEX('10_municipios'!$E$10:$E$506,MATCH(A15,'10_municipios'!$A$10:$A$506,0)) | G15: =INDEX('10_municipios'!$F$10:$F$506,MATCH(A15,'10_municipios'!$A$10:$A$506,0))
A16: 4320701 | B16: =INDEX('10_municipios'!$B$10:$B$506,MATCH(A16,'10_municipios'!$A$10:$A$506,0)) | C16: =INDEX('10_municipios'!$G$10:$G$506,MATCH(A16,'10_municipios'!$A$10:$A$506,0)) | D16: =INDEX('10_municipios'!$C$10:$C$506,MATCH(A16,'10_municipios'!$A$10:$A$506,0)) | E16: =INDEX('10_municipios'!$D$10:$D$506,MATCH(A16,'10_municipios'!$A$10:$A$506,0)) | F16: =INDEX('10_municipios'!$E$10:$E$506,MATCH(A16,'10_municipios'!$A$10:$A$506,0)) | G16: =INDEX('10_municipios'!$F$10:$F$506,MATCH(A16,'10_municipios'!$A$10:$A$506,0))
A17: 4312153 | B17: =INDEX('10_municipios'!$B$10:$B$506,MATCH(A17,'10_municipios'!$A$10:$A$506,0)) | C17: =INDEX('10_municipios'!$G$10:$G$506,MATCH(A17,'10_municipios'!$A$10:$A$506,0)) | D17: =INDEX('10_municipios'!$C$10:$C$506,MATCH(A17,'10_municipios'!$A$10:$A$506,0)) | E17: =INDEX('10_municipios'!$D$10:$D$506,MATCH(A17,'10_municipios'!$A$10:$A$506,0)) | F17: =INDEX('10_municipios'!$E$10:$E$506,MATCH(A17,'10_municipios'!$A$10:$A$506,0)) | G17: =INDEX('10_municipios'!$F$10:$F$506,MATCH(A17,'10_municipios'!$A$10:$A$506,0))
A18: 4302451 | B18: =INDEX('10_municipios'!$B$10:$B$506,MATCH(A18,'10_municipios'!$A$10:$A$506,0)) | C18: =INDEX('10_municipios'!$G$10:$G$506,MATCH(A18,'10_municipios'!$A$10:$A$506,0)) | D18: =INDEX('10_municipios'!$C$10:$C$506,MATCH(A18,'10_municipios'!$A$10:$A$506,0)) | E18: =INDEX('10_municipios'!$D$10:$D$506,MATCH(A18,'10_municipios'!$A$10:$A$506,0)) | F18: =INDEX('10_municipios'!$E$10:$E$506,MATCH(A18,'10_municipios'!$A$10:$A$506,0)) | G18: =INDEX('10_municipios'!$F$10:$F$506,MATCH(A18,'10_municipios'!$A$10:$A$506,0))
... A29: 4311239 | B29: =INDEX('10_municipios'!$B$10:$B$506,MATCH(A29,'10_municipios'!$A$10:$A$506,0)) | C29: =INDEX('10_municipios'!$G$10:$G$506,MATCH(A29,'10_municipios'!$A$10:$A$506,0)) | D29: =INDEX('10_municipios'!$C$10:$C$506,MATCH(A29,'10_municipios'!$A$10:$A$506,0)) | E29: =INDEX('10_municipios'!$D$10:$D$506,MATCH(A29,'10_municipios'!$A$10:$A$506,0)) | F29: =INDEX('10_municipios'!$E$10:$E$506,MATCH(A29,'10_municipios'!$A$10:$A$506,0)) | G29: =INDEX('10_municipios'!$F$10:$F$506,MATCH(A29,'10_municipios'!$A$10:$A$506,0))
B30: COREDE | C30: =SUM(C7:C29) | D30: =SUM(D7:D29) | E30: =SUM(E7:E29) | F30: =SUM(F7:F29) | G30: =SUM(G7:G29)
A31: Parcela do transbordamento estadual | C31: =C30/transbordo
A32: Conferência da flag, R$ mi | C32: =SUMIF('10_municipios'!$I$10:$I$506,1,'10_municipios'!$G$10:$G$506)-C30
